Metadata-Version: 2.1
Name: oapispec-v2
Version: 0.0.5
Summary: A library of decorators and functions for generating open api specs
Home-page: https://github.com/dhakiki/oapispec
Author: Ray Epps
Author-email: rayharryepps@gmail.com
License: UNKNOWN
Platform: UNKNOWN
Classifier: Development Status :: 3 - Alpha
Classifier: Intended Audience :: Developers
Classifier: Topic :: Software Development :: Libraries
Classifier: License :: OSI Approved :: MIT License
Classifier: Programming Language :: Python :: 3
Classifier: Programming Language :: Python :: 3.4
Classifier: Programming Language :: Python :: 3.5
Classifier: Programming Language :: Python :: 3.6
Classifier: Operating System :: OS Independent
Requires-Python: >=3
